dqsegdb/__init__.py
dqsegdb/_version.py
dqsegdb/apicalls.py
dqsegdb/clientutils.py
dqsegdb/jsonhelper.py
dqsegdb/ldbd.py
dqsegdb/urifunctions.py
dqsegdb/segmentdb/__init__.py
dqsegdb/segmentdb/query_engine.py
dqsegdb/segmentdb/segmentdb_utils.py
dqsegdb/tests/__init__.py
dqsegdb/tests/test_urifunctions.py
dqsegdb-3.0.0.data/scripts/ligolw_dq_query_dqsegdb
dqsegdb-3.0.0.data/scripts/ligolw_publish_threaded_dqxml_dqsegdb
dqsegdb-3.0.0.data/scripts/ligolw_segment_insert_dqsegdb
dqsegdb-3.0.0.data/scripts/ligolw_segment_query_dqsegdb
dqsegdb-3.0.0.data/scripts/ligolw_segments_from_cats_dqsegdb
dqsegdb-3.0.0.dist-info/licenses/LICENSE
dqsegdb-3.0.0.dist-info/licenses/NOTICE
dqsegdb-3.0.0.dist-info/METADATA
dqsegdb-3.0.0.dist-info/WHEEL
dqsegdb-3.0.0.dist-info/top_level.txt
dqsegdb-3.0.0.dist-info/RECORD
