Metadata-Version: 2.4
Name: dqsegdb
Version: 3.0.0
Summary: Client library for DQSegDB
Home-page: https://git.ligo.org/computing/dqsegdb/client
Author: Ryan Fisher
Author-email: ryan.fisher@ligo.org
License: GPLv3
Provides: dqsegdb
License-File: LICENSE
License-File: NOTICE
Requires-Dist: gpstime
Requires-Dist: igwn-auth-utils
Requires-Dist: igwn-ligolw>=2.0.0
Requires-Dist: lalsuite
Requires-Dist: igwn-segments
Requires-Dist: lscsoft-glue>=3.0.1
Requires-Dist: pyOpenSSL>=0.14
Requires-Dist: pyRXP
Dynamic: author
Dynamic: author-email
Dynamic: description
Dynamic: home-page
Dynamic: license
Dynamic: license-file
Dynamic: provides
Dynamic: requires-dist
Dynamic: summary
